[
	{ "s": "T001", "p": [33] },
	{ "s": "TABLA", "p": [2, 30] },
	{ "s": "TABULAR", "p": [30] },
	{ "s": "TAMBIÉN", "p": [21] },
	{ "s": "TAREA", "p": [29, 35] },
	{ "s": "TAREAS", "p": [9, 29] },
	{ "s": "TE", "p": [35, 11] },
	{ "s": "TECLA", "p": [23] },
	{ "s": "TECLADO", "p": [27] },
	{ "s": "TECLAS", "p": [25, 20] },
	{ "s": "TECNOLOGÍAS", "p": [8, 6] },
	{ "s": "TEMA", "p": [36] },
	{ "s": "TEMAS", "p": [36] },
	{ "s": "TENER", "p": [8] },
	{ "s": "TENGA", "p": [26, 24] },
	{ "s": "TEXTO", "p": [21] },
	{ "s": "TIENE", "p": [10] },
	{ "s": "TIENEN", "p": [30] },
	{ "s": "TIPO", "p": [30, 29] },
	{ "s": "TIPOS", "p": [6] },
	{ "s": "TITULO", "p": [1] },
	{ "s": "TOCA", "p": [34] },
	{ "s": "TOCAR", "p": [34, 33, 32, 22, 15, 14] },
	{ "s": "TOCARLA", "p": [32] },
	{ "s": "TODOS", "p": [30, 9, 7] },
	{ "s": "TOMAR", "p": [34, 33] },
	{ "s": "TRABAJADOR", "p": [29] },
	{ "s": "TRABAJANDO", "p": [11] },
	{ "s": "TRABAJAR", "p": [30] },
	{ "s": "TRABAJO", "p": [6] },
	{ "s": "TRANSACCIONES", "p": [27, 12, 4, 19, 18, 11, 26, 6, 31, 30, 13, 10, 9, 7, 5] },
	{ "s": "TRANSACCIÓN", "p": [26, 27, 11, 35, 34, 33, 32, 29, 19, 18, 16] },
	{ "s": "TRANSFERENCIA", "p": [5, 7, 3] },
	{ "s": "TRANSMITIDA", "p": [9] },
	{ "s": "TRANSPORT", "p": [4] },
	{ "s": "TRANSPORTE", "p": [8, 6, 5] },
	{ "s": "TRASACCION", "p": [12] },
	{ "s": "TRASACCIONES", "p": [19, 18, 16] },
	{ "s": "TRASACCIÓN", "p": [12, 19] },
	{ "s": "TRASPASAR", "p": [17] },
	{ "s": "TRATAR", "p": [26] },
	{ "s": "TRAVÉS", "p": [29] },
	{ "s": "TRÁNSITO", "p": [5] },
	{ "s": "TU", "p": [35, 27] },
	{ "s": "TUS", "p": [36] },
	{ "s": "TÉCNICOS", "p": [16] }
]